km3py/__init__.py
km3py-0.2.0.dist-info/LICENSE
km3py-0.2.0.dist-info/METADATA
km3py-0.2.0.dist-info/WHEEL
km3py-0.2.0.dist-info/top_level.txt
km3py-0.2.0.dist-info/RECORD
