Metadata-Version: 2.1
Name: km3py
Version: 0.2.0
Summary: The km3py metaproject is a collection of KM3NeT Python packages.
Home-page: https://git.km3net.de/km3py/km3py
Author: Tamas Gal
Author-email: tgal@km3net.de
License: UNKNOWN
Platform: any
Classifier: Intended Audience :: Developers
Classifier: Intended Audience :: Science/Research
Classifier: Programming Language :: Python
Requires-Python: >=3.6
Requires-Dist: km3db
Requires-Dist: km3io
Requires-Dist: km3pipe
Requires-Dist: km3pipe[dev]
Requires-Dist: km3pipe[extras]
Requires-Dist: km3net-testdata
Requires-Dist: km3astro
Requires-Dist: km3flux
Requires-Dist: km3services
